<mujoco model="platev">
  <asset>
    <mesh name="plate_mesh" file="./meshes/untextured_plate.stl" scale="1.0 1.0 1.0"/>
  </asset>
  <worldbody>
    <body>
      <body name="object">
        <geom name="plate" pos="0 0 0" mesh="plate_mesh" type="mesh" rgba="0.8 0.8 0.8 0.3" conaffinity="0" contype="0" mass="0.279" friction="0.95 0.3 0.1" group="1" condim="4"/>
      </body>
      <site rgba="1 0 0 1" size="0.005" pos="0 0 -0.012" name="bottom_site"/>
      <site rgba="0 1 0 1" size="0.005" pos="0 0 0.012" name="top_site"/>
      <site rgba="0 0 1 1" size="0.005" pos="0.029817759070200463 0.029817759070200463 0" name="horizontal_radius_site"/>
      <site rgba="0 0 0 1" size="0.005" pos="0 0 0.024" name="vertical_radius_site"/>
    </body>
  </worldbody>
</mujoco>
